pyfcm_tsn/__init__.py
pyfcm_tsn/__meta__.py
pyfcm_tsn/async_fcm.py
pyfcm_tsn/baseapi.py
pyfcm_tsn/errors.py
pyfcm_tsn/fcm.py
pyfcm_tsn-1.5.2.dist-info/LICENSE
pyfcm_tsn-1.5.2.dist-info/METADATA
pyfcm_tsn-1.5.2.dist-info/WHEEL
pyfcm_tsn-1.5.2.dist-info/top_level.txt
pyfcm_tsn-1.5.2.dist-info/RECORD
