Metadata-Version: 2.1
Name: pyfcm-tsn
Version: 1.5.2
Summary: Python client for FCM - Firebase Cloud Messaging (Android, iOS and Web)
Home-page: https://github.com/olucurious/pyfcm
Author: Emmanuel Adegbite
Author-email: olucurious@gmail.com
License: MIT License
Keywords: firebase fcm apns ios gcm android push notifications
Classifier: Development Status :: 5 - Production/Stable
Classifier: Intended Audience :: Developers
Classifier: Operating System :: OS Independent
Classifier: Programming Language :: Python
Classifier: License :: OSI Approved :: MIT License
Classifier: Topic :: Communications
Classifier: Topic :: Internet
Classifier: Topic :: Software Development :: Libraries :: Python Modules
Classifier: Topic :: Utilities
Classifier: Programming Language :: Python
Classifier: Programming Language :: Python :: 2
Classifier: Programming Language :: Python :: 2.6
Classifier: Programming Language :: Python :: 2.7
Classifier: Programming Language :: Python :: 3
Classifier: Programming Language :: Python :: 3.2
Classifier: Programming Language :: Python :: 3.3
Classifier: Programming Language :: Python :: 3.4
Classifier: Programming Language :: Python :: 3.5
License-File: LICENSE
Requires-Dist: requests
Requires-Dist: urllib3 (>=1.26.0)
Provides-Extra: test
Requires-Dist: pytest ; extra == 'test'
